README.rst
setup.py
tests/__init__.py
tests/ming_base.py
tests/sqla_base.py
tests/test_cached_query.py
tests/test_entitycached.py
tests/test_ming_validators.py
tests/test_sqla_attachments.py
tests/test_sqla_validators.py
tests/test_utils.py
tgext/__init__.py
tgext.datahelpers.egg-info/PKG-INFO
tgext.datahelpers.egg-info/SOURCES.txt
tgext.datahelpers.egg-info/dependency_links.txt
tgext.datahelpers.egg-info/entry_points.txt
tgext.datahelpers.egg-info/namespace_packages.txt
tgext.datahelpers.egg-info/not-zip-safe
tgext.datahelpers.egg-info/requires.txt
tgext.datahelpers.egg-info/top_level.txt
tgext/datahelpers/__init__.py
tgext/datahelpers/attachments.py
tgext/datahelpers/caching.py
tgext/datahelpers/fields.py
tgext/datahelpers/utils.py
tgext/datahelpers/validators.py