Metadata-Version: 1.1
Name: tgext.datahelpers
Version: 0.2.0
Summary: Helpers to manage data and attachments on TurboGears
Home-page: http://bitbucket.org/_amol_/tgext.datahelpers
Author: Alessandro Molina
Author-email: alessandro.molina@axant.it
License: MIT
Keywords: turbogears2.extension
Platform: UNKNOWN
Classifier: Environment :: Web Environment
Classifier: Topic :: Software Development :: Libraries :: Python Modules
Classifier: Framework :: TurboGears
